hubploy/__init__.py
hubploy/__main__.py
hubploy/auth.py
hubploy/commitrange.py
hubploy/config.py
hubploy/helm.py
hubploy/utils.py
hubploy-0.4.dist-info/LICENSE
hubploy-0.4.dist-info/METADATA
hubploy-0.4.dist-info/WHEEL
hubploy-0.4.dist-info/entry_points.txt
hubploy-0.4.dist-info/top_level.txt
hubploy-0.4.dist-info/RECORD
